translatesub/__init__.py
translatesub/__main__.py
translatesub/azure.py
translatesub/ffmpegutils.py
translatesub/langutils.py
translatesub-0.1.0.dist-info/entry_points.txt
translatesub-0.1.0.dist-info/METADATA
translatesub-0.1.0.dist-info/WHEEL
translatesub-0.1.0.dist-info/RECORD
