Metadata-Version: 2.1
Name: translatesub
Version: 0.1.0
Summary: Read srt subtitle from mkv file in any language, translate it to any language and append it back to the mkv
License: MIT
Keywords: translation,subtitle,movie,mkv
Author: Richard Natal
Author-email: bigous@gmail.com
Requires-Python: >=3.9,<4
Classifier: License :: OSI Approved :: MIT License
Classifier: Programming Language :: Python
Classifier: Programming Language :: Python :: 3
Classifier: Programming Language :: Python :: 3.9
Classifier: Programming Language :: Python :: 3.10
Classifier: Programming Language :: Python :: 3.11
Requires-Dist: pycountry (>=22.3.5)
Requires-Dist: pysubs2 (>=1.6.1)
Requires-Dist: python-dotenv (>=1.0.0)
Requires-Dist: requests (>=2.31.0)
